Metadata-Version: 1.0
Name: fgjhfg
Version: 1.0.1
Summary: My first lib
Home-page: UNKNOWN
Author: UNKNOWN
Author-email: uti.puti.detki@mail.ru
License: UNKNOWN
Platform: UNKNOWN
